drf_query_lang/__init__.py
drf_query_lang/apps.py
drf_query_lang/exceptions.py
drf_query_lang/permission.py
drf_query_lang/query_lang.py
drf_query_lang/settings.py
drf_query_lang/urls.py
drf_query_lang/views.py
drf_query_lang-0.0.1b1.dist-info/METADATA
drf_query_lang-0.0.1b1.dist-info/WHEEL
drf_query_lang-0.0.1b1.dist-info/top_level.txt
drf_query_lang-0.0.1b1.dist-info/RECORD
