Metadata-Version: 2.4
Name: drf-query-lang
Version: 0.0.1b1
Summary: Lightweight GraphQL alternative for django-restframework
Author-email: EL OUAZIZI Walid <contact@walidlab.dev>
License-Expression: MIT
Project-URL: Homepage, https://github.com/WalidDevIO/drf-query-lang
Classifier: Programming Language :: Python :: 3
Classifier: Framework :: Django
Classifier: Operating System :: OS Independent
Requires-Python: >=3.8
Requires-Dist: django
Requires-Dist: djangorestframework
Provides-Extra: test
Requires-Dist: pytest; extra == "test"
